bitforex/BitforexClient.py
bitforex/BitforexException.py
bitforex/Pair.py
bitforex/PeriodicChecker.py
bitforex/Timer.py
bitforex/__init__.py
bitforex/enums.py
bitforex/subscriptions.py
bitforex_aio-1.0.2.dist-info/LICENSE
bitforex_aio-1.0.2.dist-info/METADATA
bitforex_aio-1.0.2.dist-info/WHEEL
bitforex_aio-1.0.2.dist-info/top_level.txt
bitforex_aio-1.0.2.dist-info/RECORD
