Metadata-Version: 2.1
Name: bitforex-aio
Version: 1.0.2
Summary: Bitforex asynchronous python client
Home-page: https://github.com/nardew/bitforex-aio
Author: nardew
Author-email: bitforex.aio@gmail.com
License: UNKNOWN
Platform: UNKNOWN
Classifier: Development Status :: 4 - Beta
Classifier: Framework :: AsyncIO
Classifier: Intended Audience :: Developers
Classifier: Programming Language :: Python :: 3
Classifier: Programming Language :: Python :: 3.6
Classifier: Programming Language :: Python :: 3.7
Classifier: License :: OSI Approved :: MIT License
Classifier: Operating System :: OS Independent
Classifier: Topic :: Software Development :: Libraries
Classifier: Topic :: Software Development :: Libraries :: Python Modules
Classifier: Typing :: Typed
Requires-Python: >=3.6
Requires-Dist: aiohttp (==3.6.2)
Requires-Dist: websockets (==8.1)
